logical_zonotope/__init__.py
logical_zonotope/logical_zonotope.py
logical_zonotope/utility.py
logical_zonotope-0.1.0.dist-info/METADATA
logical_zonotope-0.1.0.dist-info/WHEEL
logical_zonotope-0.1.0.dist-info/top_level.txt
logical_zonotope-0.1.0.dist-info/RECORD
