Metadata-Version: 2.1
Name: logical-zonotope
Version: 0.1.0
Summary: Logical Zonotope Functions Library
Home-page: https://arxiv.org/abs/2210.08596
Author: Fargol Karamiyar
Author-email: f.karamiyar@protonmail.com
License: MIT
Platform: UNKNOWN
Classifier: Intended Audience :: Developers
Classifier: License :: OSI Approved :: MIT License
Classifier: Programming Language :: Python
Classifier: Programming Language :: Python :: 3
Classifier: Programming Language :: Python :: 3.6
Classifier: Programming Language :: Python :: 3.7
Classifier: Programming Language :: Python :: 3.8
Classifier: Programming Language :: Python :: 3.9
Classifier: Operating System :: OS Independent
